urivalidator/__init__.py
urivalidator/archive.py
urivalidator/backends.py
urivalidator/cli.py
urivalidator/colorprint.py
urivalidator/downloader.py
urivalidator/exceptions.py
urivalidator/extractor.py
urivalidator/threadpool.py
urivalidator/libs/__init__.py
urivalidator/libs/xmp.py
validate_urls-3.9.9.dist-info/METADATA
validate_urls-3.9.9.dist-info/WHEEL
validate_urls-3.9.9.dist-info/entry_points.txt
validate_urls-3.9.9.dist-info/licenses/LICENSE
validate_urls-3.9.9.dist-info/RECORD
